{
  "name": "Purple Lamp – S1 Webhook (on)",
  "nodes": [
    {
      "parameters": {
        "httpMethod": "POST",
        "path": "crowdstrike/cant/turn/this/lamp/on",
        "authentication": "headerAuth",
        "responseMode": "lastNode",
        "options": {}
      },
      "id": "...",
      "name": "Webhook (S1)",
      "type": "n8n-nodes-base.webhook",
      "typeVersion": 1,
      "position": [
        96,
        96
      ],
      "webhookId": "...",
      "credentials": {
        "httpHeaderAuth": {
          "id": "hp0XjeCEHHFJ6WPg",
          "name": "Header Auth account"
        }
      }
    },
    {
      "parameters": {
        "url": "<ip>:<port>/lamp/on",
        "sendQuery": true,
        "queryParameters": {
          "parameters": [
            {}
          ]
        },
        "options": {
          "redirect": {},
          "timeout": 10
        }
      },
      "id": "...",
      "name": "HTTP Request → Lamp (Pi)",
      "type": "n8n-nodes-base.httpRequest",
      "typeVersion": 4,
      "position": [
        432,
        96
      ]
    },
    {
      "parameters": {
        "options": {}
      },
      "id": "...",
      "name": "Respond (JSON)",
      "type": "n8n-nodes-base.respondToWebhook",
      "typeVersion": 1,
      "position": [
        800,
        96
      ]
    }
  ],
  "pinData": {},
  "connections": {
    "Webhook (S1)": {
      "main": [
        [
          {
            "node": "HTTP Request → Lamp (Pi)",
            "type": "main",
            "index": 0
          }
        ]
      ]
    },
    "HTTP Request → Lamp (Pi)": {
      "main": [
        [
          {
            "node": "Respond (JSON)",
            "type": "main",
            "index": 0
          }
        ]
      ]
    }
  },
  "active": true,
  "settings": {
    "executionOrder": "v1"
  },
  "versionId": "ff20d743-faa6-4b1b-b40a-6b2d02954b35",
  "meta": {
    "templateCredsSetupCompleted": true,
    "instanceId": "..."
  },
  "id": "...",
  "tags": []
}
